norm4phone/__init__.py
norm4phone/phone.py
norm4phone-0.1.2.dist-info/LICENSE
norm4phone-0.1.2.dist-info/METADATA
norm4phone-0.1.2.dist-info/WHEEL
norm4phone-0.1.2.dist-info/top_level.txt
norm4phone-0.1.2.dist-info/RECORD
