Metadata-Version: 2.1
Name: norm4phone
Version: 0.1.2
Summary: a tool to normalize different writing of phone numbers into standard format
Home-page: https://github.com/xuxingya/norm4phone
Author: xingya.xu
Author-email: xingya.xu@gmail.com
License: MIT License
Platform: UNKNOWN
